winrecon/__init__.py
winrecon/file_utils.py
winrecon/cf/__init__.py
winrecon/cf/c_functions.py
winrecon/cf/defines.py
winrecon/cf/netapi32_high.py
winrecon/cf/sid.py
winrecon-0.0.1.dist-info/METADATA
winrecon-0.0.1.dist-info/WHEEL
winrecon-0.0.1.dist-info/top_level.txt
winrecon-0.0.1.dist-info/zip-safe
winrecon-0.0.1.dist-info/RECORD
