Metadata-Version: 2.1
Name: winrecon
Version: 0.0.1
Summary: Python interface for a few windows API calls
Home-page: https://github.com/skelsec/winrecon
Author: Tamas Jos
Author-email: info@skelsec.com
License: UNKNOWN
Platform: UNKNOWN
Classifier: Programming Language :: Python :: 3.6
Classifier: License :: OSI Approved :: MIT License
Classifier: Operating System :: OS Independent
Requires-Python: >=3.6
